jupyterlab_cell_runner/__init__.py
jupyterlab_cell_runner/labextension/package.json
jupyterlab_cell_runner/labextension/static/509.8c0938c1f72abd34e0bd.js
jupyterlab_cell_runner/labextension/static/728.4288bee361b1a42271a0.js
jupyterlab_cell_runner/labextension/static/remoteEntry.917c52fc1b1ef18ceaef.js
jupyterlab_cell_runner/labextension/static/style.js
jupyterlab_cell_runner/labextension/static/third-party-licenses.json
jupyterlab_cell_runner-0.1.0.data/data/share/jupyter/labextensions/jupyterlab-cell-runner/package.json
jupyterlab_cell_runner-0.1.0.data/data/share/jupyter/labextensions/jupyterlab-cell-runner/static/509.8c0938c1f72abd34e0bd.js
jupyterlab_cell_runner-0.1.0.data/data/share/jupyter/labextensions/jupyterlab-cell-runner/static/728.4288bee361b1a42271a0.js
jupyterlab_cell_runner-0.1.0.data/data/share/jupyter/labextensions/jupyterlab-cell-runner/static/remoteEntry.917c52fc1b1ef18ceaef.js
jupyterlab_cell_runner-0.1.0.data/data/share/jupyter/labextensions/jupyterlab-cell-runner/static/style.js
jupyterlab_cell_runner-0.1.0.data/data/share/jupyter/labextensions/jupyterlab-cell-runner/static/third-party-licenses.json
jupyterlab_cell_runner-0.1.0.data/data/share/jupyter/labextensions/jupyterlab-cell-runner/install.json
jupyterlab_cell_runner-0.1.0.dist-info/METADATA
jupyterlab_cell_runner-0.1.0.dist-info/WHEEL
jupyterlab_cell_runner-0.1.0.dist-info/RECORD
