Metadata-Version: 2.4
Name: jupyterlab-cell-runner
Version: 0.1.0
Summary: JupyterLab extension for BlocklyBot - programmatic cell execution via postMessage
Project-URL: Homepage, https://github.com/mlzboy/jupyterlab-cell-runner
Author: mlzboy
License: MIT
Classifier: Framework :: Jupyter
Classifier: Framework :: Jupyter :: JupyterLab
Classifier: Framework :: Jupyter :: JupyterLab :: 4
Classifier: Framework :: Jupyter :: JupyterLab :: Extensions
Classifier: License :: OSI Approved :: MIT License
Classifier: Programming Language :: Python :: 3
Requires-Python: >=3.8
Requires-Dist: jupyterlab<5,>=4.0.0
